{
  "source": "VnExpress RSS",
  "updated": "2026-02-13T10:29:22.067656Z",
  "updated_vn": "2026-02-13T17:29:22.067659+07:00",
  "schedule_time": "17:29",
  "articles": [
    {
      "id": "https://vnexpress.net/ancelotti-dan-dat-brazil-them-bon-nam-5040903.html",
      "title": "Ancelotti dẫn dắt Brazil thêm bốn năm",
      "link": "https://vnexpress.net/ancelotti-dan-dat-brazil-them-bon-nam-5040903.html",
      "pubDate": "Fri, 13 Feb 2026 16:30:10 +0700",
      "description": "<a href=\"https://vnexpress.net/ancelotti-dan-dat-brazil-them-bon-nam-5040903.html\"><img src=\"https://vcdn1-thethao.vnecdn.net/2026/02/13/images2234570764scaled1-177097-8379-9794-1770970683.jpg?w=1200&amp;h=0&amp;q=100&amp;dpr=1&amp;fit=crop&amp;s=YW9vvXBVQAoPcpl9Iag-ZA\" /></a>Carlo Ancelotti chuẩn bị ký hợp đồng mới với Liên đoàn bóng đá Brazil (CBF) để tiếp tục làm HLV trưởng đội tuyển nước này đến năm 2030.",
      "image": ""
    },
    {
      "id": "https://vnexpress.net/phu-hung-life-bo-nhiem-tong-giam-doc-moi-5040951.html",
      "title": "Phú Hưng Life bổ nhiệm Tổng giám đốc mới",
      "link": "https://vnexpress.net/phu-hung-life-bo-nhiem-tong-giam-doc-moi-5040951.html",
      "pubDate": "Fri, 13 Feb 2026 16:30:00 +0700",
      "description": "<a href=\"https://vnexpress.net/phu-hung-life-bo-nhiem-tong-giam-doc-moi-5040951.html\"><img src=\"https://vcdn1-kinhdoanh.vnecdn.net/2026/02/13/picture1-1770974890-1770974919-6488-1770975041.png?w=1200&amp;h=0&amp;q=100&amp;dpr=1&amp;fit=crop&amp;s=SseZxcNuelBDFBzWOhLCtQ\" /></a>Bà Yong Lai Yin được bổ nhiệm giữ chức Tổng giám đốc Công ty Cổ phần Bảo hiểm Nhân thọ Phú Hưng, từ ngày 19/1.",
      "image": ""
    },
    {
      "id": "https://vnexpress.net/hotgirl-esports-thai-lan-bi-bat-vi-gian-lan-o-tran-gap-viet-nam-5040947.html",
      "title": "Hotgirl esports Thái Lan bị bắt vì gian lận ở trận gặp Việt Nam",
      "link": "https://vnexpress.net/hotgirl-esports-thai-lan-bi-bat-vi-gian-lan-o-tran-gap-viet-nam-5040947.html",
      "pubDate": "Fri, 13 Feb 2026 16:25:01 +0700",
      "description": "<a href=\"https://vnexpress.net/hotgirl-esports-thai-lan-bi-bat-vi-gian-lan-o-tran-gap-viet-nam-5040947.html\"><img src=\"https://vcdn1-thethao.vnecdn.net/2026/02/13/screenshot-2026-02-13-at-16-23-5262-6063-1770974623.png?w=1200&amp;h=0&amp;q=100&amp;dpr=1&amp;fit=crop&amp;s=qH7z3TuHsUVX_L9dfJC3tw\" /></a>Cục Điều tra Trung ương Thái Lan (CIB) đã bắt tuyển thủ Wasarin Naraphat và Cheerio bị buộc tội gian lận khi thi đấu esports tại SEA Games 33.",
      "image": ""
    },
    {
      "id": "https://vnexpress.net/hang-nghin-khach-du-xuan-do-ve-duong-hoa-phu-my-hung-5040938.html",
      "title": "Hàng nghìn khách du xuân đổ về đường hoa Phú Mỹ Hưng",
      "link": "https://vnexpress.net/hang-nghin-khach-du-xuan-do-ve-duong-hoa-phu-my-hung-5040938.html",
      "pubDate": "Fri, 13 Feb 2026 16:15:00 +0700",
      "description": "<a href=\"https://vnexpress.net/hang-nghin-khach-du-xuan-do-ve-duong-hoa-phu-my-hung-5040938.html\"><img src=\"https://vcdn1-kinhdoanh.vnecdn.net/2026/02/13/3-2-JPG-1770973651.jpg?w=1200&amp;h=0&amp;q=100&amp;dpr=1&amp;fit=crop&amp;s=hZCNuTlnm3Y-ZJCrZSPn1g\" /></a>Đường hoa chủ đề \"Xuân gắn kết\" mở cửa từ 11/2 (24 tháng Chạp) trang trí nhiều tiểu cảnh, mô hình ngựa cao 4,5 m, thu hút hàng nghìn lượt khách tham quan.",
      "image": ""
    },
    {
      "id": "https://vnexpress.net/di-nguoc-chieu-vong-xuyen-xe-may-vo-nat-vi-huc-vao-oto-5040930.html",
      "title": "Đi ngược chiều vòng xuyến, xe máy vỡ nát vì húc vào ôtô",
      "link": "https://vnexpress.net/di-nguoc-chieu-vong-xuyen-xe-may-vo-nat-vi-huc-vao-oto-5040930.html",
      "pubDate": "Fri, 13 Feb 2026 16:14:18 +0700",
      "description": "<a href=\"https://vnexpress.net/di-nguoc-chieu-vong-xuyen-xe-may-vo-nat-vi-huc-vao-oto-5040930.html\"><img src=\"https://vcdn1-vnexpress.vnecdn.net/2026/02/13/ezgif592739424558bed7-17709726-6669-3356-1770972657.gif?w=1200&amp;h=0&amp;q=100&amp;dpr=1&amp;fit=crop&amp;s=wfOxfgxEDejtbc6evMEpmw&amp;t=image\" /></a>Xe máy đi ngược chiều tại vòng xuyến va chạm xe bán tải, khiến hai người ngã xuống đường, phương tiện hư hỏng nặng, ngày 13/2.",
      "image": ""
    }
  ],
  "total_articles": 5
}