{
  "source": "VnExpress RSS",
  "updated": "2026-01-16T23:11:44.386986Z",
  "updated_vn": "2026-01-17T06:11:44.386990+07:00",
  "schedule_time": "06:11",
  "articles": [
    {
      "id": "https://vnexpress.net/khon-kho-vi-song-chung-voi-gau-260-kg-duoi-gam-nha-5006578.html",
      "title": "Khốn khổ vì sống chung với gấu 260 kg dưới gầm nhà",
      "link": "https://vnexpress.net/khon-kho-vi-song-chung-voi-gau-260-kg-duoi-gam-nha-5006578.html",
      "pubDate": "Sat, 17 Jan 2026 05:43:00 +0700",
      "description": "<a href=\"https://vnexpress.net/khon-kho-vi-song-chung-voi-gau-260-kg-duoi-gam-nha-5006578.html\"><img src=\"https://vcdn1-giadinh.vnecdn.net/2026/01/16/untitled-6-1768557801-17685578-2707-3155-1768558430.jpg?w=1200&amp;h=0&amp;q=100&amp;dpr=1&amp;fit=crop&amp;s=jTEmGY8-hUMj8gDwqk1Z6Q\" /></a>Ông Ken Johnson mất ăn mất ngủ, phải tắm nước lạnh giữa mùa đông vì con gấu nặng 260 kg chọn gầm nhà ông làm nơi trú đông suốt hai tháng.",
      "image": ""
    },
    {
      "id": "https://vnexpress.net/tan-hlv-real-moi-chuyen-tren-san-la-trach-nhiem-cua-toi-5006637.html",
      "title": "Tân HLV Real: 'Mọi chuyện trên sân là trách nhiệm của tôi'",
      "link": "https://vnexpress.net/tan-hlv-real-moi-chuyen-tren-san-la-trach-nhiem-cua-toi-5006637.html",
      "pubDate": "Sat, 17 Jan 2026 05:42:54 +0700",
      "description": "<a href=\"https://vnexpress.net/tan-hlv-real-moi-chuyen-tren-san-la-trach-nhiem-cua-toi-5006637.html\"><img src=\"https://vcdn1-thethao.vnecdn.net/2026/01/16/arbeloa-png-1768578687-1768578-2456-3861-1768578747.png?w=1200&amp;h=0&amp;q=100&amp;dpr=1&amp;fit=crop&amp;s=dIU7WrBru6DsEHGmMFZDrw\" /></a>HLV Alvaro Arbeloa bảo vệ các cầu thủ và kêu gọi người hâm mộ ủng hộ, trước trận Real Madrid gặp Levante ở vòng 20 La Liga.",
      "image": ""
    },
    {
      "id": "https://vnexpress.net/ong-phan-minh-thong-lam-nong-nghiep-la-mo-vang-ben-vung-5006559.html",
      "title": "Ông Phan Minh Thông: 'Làm nông nghiệp là mỏ vàng bền vững'",
      "link": "https://vnexpress.net/ong-phan-minh-thong-lam-nong-nghiep-la-mo-vang-ben-vung-5006559.html",
      "pubDate": "Sat, 17 Jan 2026 05:00:00 +0700",
      "description": "<a href=\"https://vnexpress.net/ong-phan-minh-thong-lam-nong-nghiep-la-mo-vang-ben-vung-5006559.html\"><img src=\"https://vcdn1-kinhdoanh.vnecdn.net/2026/01/16/phanminhthong3-1768574328-1768-5460-6971-1768574589.jpg?w=1200&amp;h=0&amp;q=100&amp;dpr=1&amp;fit=crop&amp;s=4olF6LQbOAtd9DjaMEZrgg\" /></a>Chủ tịch Tập đoàn Phúc Sinh Phan Minh Thông cho rằng nông nghiệp là \"mỏ vàng\" bền vững nếu doanh nghiệp bỏ tư duy bán thô, chuyển sang chế biến sâu và rào cản chính sách được gỡ bỏ.",
      "image": ""
    },
    {
      "id": "https://vnexpress.net/quyen-mien-tru-tuyet-doi-cua-dac-vu-ice-thoi-ong-trump-5006265.html",
      "title": "Quyền 'miễn trừ tuyệt đối' của đặc vụ ICE thời ông Trump",
      "link": "https://vnexpress.net/quyen-mien-tru-tuyet-doi-cua-dac-vu-ice-thoi-ong-trump-5006265.html",
      "pubDate": "Sat, 17 Jan 2026 05:00:00 +0700",
      "description": "<a href=\"https://vnexpress.net/quyen-mien-tru-tuyet-doi-cua-dac-vu-ice-thoi-ong-trump-5006265.html\"><img src=\"https://vcdn1-vnexpress.vnecdn.net/2026/01/16/download1-1768536898-1377-1768537369.jpg?w=1200&amp;h=0&amp;q=100&amp;dpr=1&amp;fit=crop&amp;s=_2dnn-f2L5z_1RRKF073LQ\" /></a>Chính quyền Trump tuyên bố các đặc vụ ICE được hưởng \"quyền miễn trừ tuyệt đối\" sau vụ nổ súng tại Minnesota, bất chấp quy định nghiêm ngặt về sử dụng vũ lực.",
      "image": ""
    },
    {
      "id": "https://vnexpress.net/loat-tv-65-inch-chay-google-tv-gia-tot-5004801.html",
      "title": "Loạt TV 65 inch chạy Google TV giá tốt",
      "link": "https://vnexpress.net/loat-tv-65-inch-chay-google-tv-gia-tot-5004801.html",
      "pubDate": "Sat, 17 Jan 2026 05:00:00 +0700",
      "description": "<a href=\"https://vnexpress.net/loat-tv-65-inch-chay-google-tv-gia-tot-5004801.html\"><img src=\"https://vcdn1-vnexpress.vnecdn.net/2026/01/14/image-2-1768389677-1768390078-4518-1768390144.jpg?w=1200&amp;h=0&amp;q=100&amp;dpr=1&amp;fit=crop&amp;s=4hfsSn08vctLvm4AFeHFJg\" /></a>Các mẫu TV từ Sony, Xiaomi, K-Elec, TCL hay Coocaa có kích thước 65 inch, chạy Google TV điều khiển giọng nói tiếng Việt.",
      "image": ""
    }
  ],
  "total_articles": 5
}