{
  "source": "VnExpress RSS",
  "updated": "2026-04-01T04:38:32.576080Z",
  "updated_vn": "2026-04-01T11:38:32.576085+07:00",
  "schedule_time": "11:38",
  "articles": [
    {
      "id": "https://vnexpress.net/du-khach-say-xin-o-bali-bi-vo-si-dia-phuong-siet-co-5057089.html",
      "title": "Du khách say xỉn ở Bali bị võ sĩ địa phương siết cổ",
      "link": "https://vnexpress.net/du-khach-say-xin-o-bali-bi-vo-si-dia-phuong-siet-co-5057089.html",
      "pubDate": "Wed, 01 Apr 2026 11:34:24 +0700",
      "description": "<a href=\"https://vnexpress.net/du-khach-say-xin-o-bali-bi-vo-si-dia-phuong-siet-co-5057089.html\"><img src=\"https://vcdn1-dulich.vnecdn.net/2026/04/01/imgi-1-balinese-fighter-gym-ow-6285-7055-1775013941.jpg?w=1200&amp;h=0&amp;q=100&amp;dpr=1&amp;fit=crop&amp;s=r1Wvs-ppfofb2_D2axVTRg\" /></a>Du khách Nga say xỉn, có hành vi sàm sỡ phụ nữ đã bị một võ sĩ Bali siết cổ đến khi suýt ngất lịm.",
      "image": ""
    },
    {
      "id": "https://vnexpress.net/son-la-co-tan-giam-doc-cong-an-tinh-5057118.html",
      "title": "Sơn La có tân Giám đốc Công an tỉnh",
      "link": "https://vnexpress.net/son-la-co-tan-giam-doc-cong-an-tinh-5057118.html",
      "pubDate": "Wed, 01 Apr 2026 11:32:51 +0700",
      "description": "<a href=\"https://vnexpress.net/son-la-co-tan-giam-doc-cong-an-tinh-5057118.html\"><img src=\"https://vcdn1-vnexpress.vnecdn.net/2026/04/01/a5-1775016908-1775016935-17750-1318-2728-1775017245.jpg?w=1200&amp;h=0&amp;q=100&amp;dpr=1&amp;fit=crop&amp;s=aapxgO_1KSIjoQknL3pAiw\" /></a>Đại tá Nguyễn Minh Tuấn, Phó chánh Văn phòng Cơ quan Cảnh sát điều tra Bộ Công an, được điều động, bổ nhiệm làm Giám đốc Công an tỉnh Sơn La.",
      "image": ""
    },
    {
      "id": "https://vnexpress.net/messi-nhuong-phat-den-trong-chien-thang-5-0-cua-argentina-5057127.html",
      "title": "Messi nhường phạt đền trong chiến thắng 5-0 của Argentina",
      "link": "https://vnexpress.net/messi-nhuong-phat-den-trong-chien-thang-5-0-cua-argentina-5057127.html",
      "pubDate": "Wed, 01 Apr 2026 11:30:39 +0700",
      "description": "<a href=\"https://vnexpress.net/messi-nhuong-phat-den-trong-chien-thang-5-0-cua-argentina-5057127.html\"><img src=\"https://vcdn1-thethao.vnecdn.net/2026/04/01/messi-png-1775017141-177501726-6436-7929-1775017374.png?w=1200&amp;h=0&amp;q=100&amp;dpr=1&amp;fit=crop&amp;s=TH0ynfb7bl1C94N2c0YwCQ\" /></a>Đội trưởng Lionel Messi ghi một bàn, một kiến tạo và một lần nhường phạt đền khi Argentina thắng Zambia 5-0 trong trận giao hữu cuối cùng trước World Cup 2026.",
      "image": ""
    },
    {
      "id": "https://vnexpress.net/du-kien-hien-thi-thong-tin-ly-lich-tu-phap-tren-vneid-tu-1-7-5057024.html",
      "title": "Dự kiến hiển thị thông tin lý lịch tư pháp trên VNeID từ 1/7",
      "link": "https://vnexpress.net/du-kien-hien-thi-thong-tin-ly-lich-tu-phap-tren-vneid-tu-1-7-5057024.html",
      "pubDate": "Wed, 01 Apr 2026 11:28:40 +0700",
      "description": "<a href=\"https://vnexpress.net/du-kien-hien-thi-thong-tin-ly-lich-tu-phap-tren-vneid-tu-1-7-5057024.html\"><img src=\"https://vcdn1-vnexpress.vnecdn.net/2026/04/01/2-1775014186-1775014310-7976-1775014432.jpg?w=1200&amp;h=0&amp;q=100&amp;dpr=1&amp;fit=crop&amp;s=ZnljdCh7Xp5dYM4nn55Q1g\" /></a>Bộ Công an đề xuất hiển thị thông tin lý lịch tư pháp trên ứng dụng VNeID kể từ khi có kết quả cấp phiếu lý lịch tư pháp bản điện tử lần đầu.",
      "image": ""
    },
    {
      "id": "https://vnexpress.net/hoa-hau-phuong-oanh-toi-tu-lap-tu-nam-16-tuoi-5056779.html",
      "title": "Hoa hậu Phương Oanh: 'Tôi tự lập từ năm 16 tuổi'",
      "link": "https://vnexpress.net/hoa-hau-phuong-oanh-toi-tu-lap-tu-nam-16-tuoi-5056779.html",
      "pubDate": "Wed, 01 Apr 2026 11:14:13 +0700",
      "description": "<a href=\"https://vnexpress.net/hoa-hau-phuong-oanh-toi-tu-lap-tu-nam-16-tuoi-5056779.html\"><img src=\"https://vcdn1-giaitri.vnecdn.net/2026/03/31/PhanPhuongOanh2-1774948231-6563-1774964788.jpg?w=1200&amp;h=0&amp;q=100&amp;dpr=1&amp;fit=crop&amp;s=yazSQfLcBmZIOjPJeQaULg\" /></a>Miss World Vietnam 2025 Phan Phương Oanh cho biết từ năm 16 tuổi đã làm gia sư, người mẫu, kiếm tiền chi trả học phí, đầu tư thi nhan sắc.",
      "image": ""
    }
  ],
  "total_articles": 5
}