{
  "source": "VnExpress RSS",
  "updated": "2026-02-20T04:04:41.537273Z",
  "updated_vn": "2026-02-20T11:04:41.537276+07:00",
  "schedule_time": "11:04",
  "articles": [
    {
      "id": "https://vnexpress.net/hai-nguoi-nuoc-ngoai-giang-bay-doi-tien-ao-usdt-5042433.html",
      "title": "Hai người nước ngoài giăng bẫy đổi tiền ảo USDT",
      "link": "https://vnexpress.net/hai-nguoi-nuoc-ngoai-giang-bay-doi-tien-ao-usdt-5042433.html",
      "pubDate": "Fri, 20 Feb 2026 10:32:41 +0700",
      "description": "<a href=\"https://vnexpress.net/hai-nguoi-nuoc-ngoai-giang-bay-doi-tien-ao-usdt-5042433.html\"><img src=\"https://vcdn1-vnexpress.vnecdn.net/2026/02/20/untitled-1-copy-1771556889-177-6426-6005-1771557008.jpg?w=1200&amp;h=0&amp;q=100&amp;dpr=1&amp;fit=crop&amp;s=pZ7-YcXJ_LxsolxXKvO9KA\" /></a>Bi Shuang và Cui Feiyang vờ cần đổi tiền ảo USDT sang tiền Việt Nam để dụ nạn nhân đến điểm hẹn rồi chiếm đoạt tài sản.",
      "image": ""
    },
    {
      "id": "https://vnexpress.net/em-trai-vua-charles-iii-duoc-canh-sat-tha-5042429.html",
      "title": "Em trai Vua Charles III được cảnh sát thả",
      "link": "https://vnexpress.net/em-trai-vua-charles-iii-duoc-canh-sat-tha-5042429.html",
      "pubDate": "Fri, 20 Feb 2026 10:12:59 +0700",
      "description": "<a href=\"https://vnexpress.net/em-trai-vua-charles-iii-duoc-canh-sat-tha-5042429.html\"><img src=\"https://vcdn1-vnexpress.vnecdn.net/2026/02/20/3ff286db-ccaa-4cea-99b5-eafdae-8702-1331-1771555444.webp?w=1200&amp;h=0&amp;q=100&amp;dpr=1&amp;fit=crop&amp;s=aXTfdKyC15QZOy2ClFNXEQ\" /></a>Cựu hoàng tử Anh Andrew được tại ngoại khi cảnh sát đang tiếp tục điều tra, sau khi ông bị bắt với nghi ngờ gửi tài liệu mật của chính phủ cho tỷ phú ấu dâm Epstein.",
      "image": ""
    },
    {
      "id": "https://vnexpress.net/sao-euphoria-qua-doi-5042426.html",
      "title": "Sao 'Euphoria' qua đời",
      "link": "https://vnexpress.net/sao-euphoria-qua-doi-5042426.html",
      "pubDate": "Fri, 20 Feb 2026 10:11:09 +0700",
      "description": "<a href=\"https://vnexpress.net/sao-euphoria-qua-doi-5042426.html\"><img src=\"https://vcdn1-giaitri.vnecdn.net/2026/02/20/eric-dane-2-1771555238-1771555-5146-8640-1771555534.png?w=1200&amp;h=0&amp;q=100&amp;dpr=1&amp;fit=crop&amp;s=_e4PYf75U7skS1G1x1euQQ\" /></a>Eric Dane, diễn viên đóng \"Euphoria\" qua đời ở tuổi 54, sau gần một năm phát hiện bệnh liên quan vấn đề thần kinh.",
      "image": ""
    },
    {
      "id": "https://vnexpress.net/gia-vang-giang-co-quanh-5-000-usd-5042418.html",
      "title": "Giá vàng giằng co quanh 5.000 USD",
      "link": "https://vnexpress.net/gia-vang-giang-co-quanh-5-000-usd-5042418.html",
      "pubDate": "Fri, 20 Feb 2026 10:03:24 +0700",
      "description": "<a href=\"https://vnexpress.net/gia-vang-giang-co-quanh-5-000-usd-5042418.html\"><img src=\"https://vcdn1-kinhdoanh.vnecdn.net/2026/02/20/Gold-1771552932-6348-1771553115.webp?w=1200&amp;h=0&amp;q=100&amp;dpr=1&amp;fit=crop&amp;s=GJkPDf8nNa55BrhiXSSSxg\" /></a>Giá vàng thế giới dao động trong biên độ hẹp, quanh 5.000 USD, khi nhà đầu tư tiếp tục theo dõi căng thẳng Mỹ - Iran và chờ thêm dữ liệu lạm phát.",
      "image": ""
    },
    {
      "id": "https://vnexpress.net/lich-thi-le-phi-thi-danh-gia-nang-luc-cua-cac-truong-dai-hoc-nam-2026-chi-tiet-nhat-5039470.html",
      "title": "Lịch thi đánh giá năng lực, tư duy của 9 đại học năm 2026",
      "link": "https://vnexpress.net/lich-thi-le-phi-thi-danh-gia-nang-luc-cua-cac-truong-dai-hoc-nam-2026-chi-tiet-nhat-5039470.html",
      "pubDate": "Fri, 20 Feb 2026 10:01:00 +0700",
      "description": "<a href=\"https://vnexpress.net/lich-thi-le-phi-thi-danh-gia-nang-luc-cua-cac-truong-dai-hoc-nam-2026-chi-tiet-nhat-5039470.html\"><img src=\"https://vcdn1-vnexpress.vnecdn.net/2026/02/12/1ead0a32ed13634d3a02-177087324-2236-1336-1770873373.jpg?w=1200&amp;h=0&amp;q=100&amp;dpr=1&amp;fit=crop&amp;s=SSNDylPM8Kga4dgnAM3hMA\" /></a>Các đợt thi đánh giá năng lực, tư duy sau Tết diễn ra từ tháng 3 đến 6, lệ phí cao nhất là 2 triệu đồng.",
      "image": ""
    }
  ],
  "total_articles": 5
}