{
  "source": "VnExpress RSS",
  "updated": "2026-05-10T08:48:41.433515Z",
  "updated_vn": "2026-05-10T15:48:41.433519+07:00",
  "schedule_time": "15:48",
  "articles": [
    {
      "id": "https://vnexpress.net/mien-bac-va-trung-tuan-toi-nang-nong-5072139.html",
      "title": "Miền Bắc và Trung tuần tới nắng nóng",
      "link": "https://vnexpress.net/mien-bac-va-trung-tuan-toi-nang-nong-5072139.html",
      "pubDate": "Sun, 10 May 2026 15:10:05 +0700",
      "description": "<a href=\"https://vnexpress.net/mien-bac-va-trung-tuan-toi-nang-nong-5072139.html\"><img src=\"https://vcdn1-vnexpress.vnecdn.net/2026/05/10/nghi-le-jpg-1778400540-2275-1778400565.jpg?w=1200&amp;h=0&amp;q=100&amp;dpr=1&amp;fit=crop&amp;s=Zbeq74kS9SvLLHqy9OzmLA\" /></a>Miền Bắc và Trung xuất hiện nắng nóng diện rộng từ giữa tuần tới với nền nhiệt có nơi trên 39 độ C; Nam Bộ mùa mưa đến muộn hơn trung bình nhiều năm.",
      "image": ""
    },
    {
      "id": "https://vnexpress.net/trung-quoc-tang-manh-xuat-nhap-khau-5072090.html",
      "title": "Trung Quốc tăng mạnh xuất nhập khẩu",
      "link": "https://vnexpress.net/trung-quoc-tang-manh-xuat-nhap-khau-5072090.html",
      "pubDate": "Sun, 10 May 2026 15:05:00 +0700",
      "description": "<a href=\"https://vnexpress.net/trung-quoc-tang-manh-xuat-nhap-khau-5072090.html\"><img src=\"https://vcdn1-kinhdoanh.vnecdn.net/2026/05/10/2025t155120z-mt1sipa000617rar-7767-4816-1778385184.jpg?w=1200&amp;h=0&amp;q=100&amp;dpr=1&amp;fit=crop&amp;s=UTw5rpOE5I9BvtRdvXdz3w\" /></a>Bất chấp căng thẳng Trung Đông, kim ngạch xuất nhập khẩu tháng 4 của Trung Quốc vẫn tăng trên 14% nhờ nhu cầu tích trữ hàng hóa toàn cầu, đơn hàng AI.",
      "image": ""
    },
    {
      "id": "https://vnexpress.net/giao-vien-nhan-vien-hop-dong-sap-duoc-tra-luong-sau-gan-6-thang-treo-5072118.html",
      "title": "Giáo viên, nhân viên hợp đồng sắp được trả lương sau gần 6 tháng 'treo'",
      "link": "https://vnexpress.net/giao-vien-nhan-vien-hop-dong-sap-duoc-tra-luong-sau-gan-6-thang-treo-5072118.html",
      "pubDate": "Sun, 10 May 2026 14:58:02 +0700",
      "description": "<a href=\"https://vnexpress.net/giao-vien-nhan-vien-hop-dong-sap-duoc-tra-luong-sau-gan-6-thang-treo-5072118.html\"><img src=\"https://vcdn1-vnexpress.vnecdn.net/2026/05/10/giao-vien-mam-non-1778391759-3656-1778399748.jpg?w=1200&amp;h=0&amp;q=100&amp;dpr=1&amp;fit=crop&amp;s=LHDay4L9XQvc9DHxwxqAOQ\" /></a>Hơn 200 giáo viên, hợp đồng sẽ được trả lương sau gần nửa năm bị \"treo\" do thay đổi chính sách, tổng khoảng 8,7 tỷ đồng,",
      "image": ""
    },
    {
      "id": "https://vnexpress.net/viet-nam-han-quoc-quyet-chien-vi-ve-u17-world-cup-5072142.html",
      "title": "Việt Nam - Hàn Quốc: Quyết chiến vì vé U17 World Cup",
      "link": "https://vnexpress.net/viet-nam-han-quoc-quyet-chien-vi-ve-u17-world-cup-5072142.html",
      "pubDate": "Sun, 10 May 2026 14:49:31 +0700",
      "description": "<a href=\"https://vnexpress.net/viet-nam-han-quoc-quyet-chien-vi-ve-u17-world-cup-5072142.html\"><img src=\"https://vcdn1-thethao.vnecdn.net/2026/05/10/z7798655312362f39830b96a1bc3ea-6758-3522-1778400094.jpg?w=1200&amp;h=0&amp;q=100&amp;dpr=1&amp;fit=crop&amp;s=0v7zFhqeKKzZcTANvryN5g\" /></a>Một kết quả tốt trước Hàn Quốc ở lượt hai bảng C giải U17 châu Á hôm nay sẽ giúp thầy trò HLV Cristiano Roland chạm tay vào tấm vé dự U17 World Cup.",
      "image": ""
    },
    {
      "id": "https://vnexpress.net/hlv-brentford-khong-hieu-vi-sao-man-city-thoat-phat-den-5072149.html",
      "title": "HLV Brentford: 'Không hiểu vì sao Man City thoát phạt đền'",
      "link": "https://vnexpress.net/hlv-brentford-khong-hieu-vi-sao-man-city-thoat-phat-den-5072149.html",
      "pubDate": "Sun, 10 May 2026 14:48:43 +0700",
      "description": "<a href=\"https://vnexpress.net/hlv-brentford-khong-hieu-vi-sao-man-city-thoat-phat-den-5072149.html\"><img src=\"https://vcdn1-thethao.vnecdn.net/2026/05/10/brentford-man-city-jpeg-177839-3190-5016-1778399227.jpg?w=1200&amp;h=0&amp;q=100&amp;dpr=1&amp;fit=crop&amp;s=K7eW6lE0noJlYlzP_m41Gg\" /></a>HLV Keith Andrews cho rằng Brentford bị từ chối một quả phạt đền khó hiểu trong trận thua Man City 0-3 ở vòng 36 Ngoại hạng Anh.",
      "image": ""
    }
  ],
  "total_articles": 5
}